gamelocker/__init__.py
gamelocker/api.py
gamelocker/datatypes.py
gamelocker/janus.py
gamelocker/strings.py
python_gamelocker-0.4.0.dist-info/DESCRIPTION.rst
python_gamelocker-0.4.0.dist-info/METADATA
python_gamelocker-0.4.0.dist-info/RECORD
python_gamelocker-0.4.0.dist-info/WHEEL
python_gamelocker-0.4.0.dist-info/metadata.json
python_gamelocker-0.4.0.dist-info/top_level.txt
