Metadata-Version: 2.0
Name: python-gamelocker
Version: 0.4.0
Summary: Python Gamelocker API Wrapper
Home-page: https://git.schneefux.xyz/schneefux/python-gamelocker
Author: schneefux
Author-email: schneefux+pypi_schneefux@schneefux.xyz
License: UNKNOWN
Platform: UNKNOWN
Requires-Dist: requests
